Metadata-Version: 2.1
Name: speed-friending-matcher
Version: 0.1.1.dev0
Summary: Matching software for speed friending events.
Home-page: https://github.com/machinekoder/speed-friending-matcher/
Author: Alexander Rössler
Author-email: alex@machinekoder.com
License: MIT
Platform: UNKNOWN
Provides-Extra: dev
